{
  "colors": [
    {
      "$value": "rgba(247, 245, 243, 0.85)",
      "$type": "color",
      "docs": {
        "category": "colors",
        "type": "modal",
        "example": "color",
        "description": "The background overlay for modal"
      },
      "filePath": "tokens/global/modal.json",
      "isSource": false,
      "original": {
        "$value": "{options.color.warm-grey-025-85}",
        "$type": "color",
        "docs": {
          "category": "colors",
          "type": "modal",
          "example": "color",
          "description": "The background overlay for modal"
        }
      },
      "name": "cdr-color-background-modal-overlay",
      "attributes": {
        "category": "color",
        "type": "background",
        "item": "modal",
        "subitem": "overlay",
        "deprecated": false
      },
      "key": "{color.background.modal.overlay}"
    }
  ]
}